[
    {
        "id": "9bff0843.525ed8",
        "type": "tab",
        "label": "Flow 1",
        "disabled": false,
        "info": ""
    },
    {
        "id": "ef5f38e5.f1eb68",
        "type": "inject",
        "z": "9bff0843.525ed8",
        "name": "",
        "props": [
            {
                "p": "payload"
            },
            {
                "p": "topic",
                "vt": "str"
            }
        ],
        "repeat": "",
        "crontab": "",
        "once": false,
        "onceDelay": 0.1,
        "topic": "",
        "payload": "{\"temp_in\":4}",
        "payloadType": "json",
        "x": 280,
        "y": 280,
        "wires": [
            [
                "aa03b7a9.435998"
            ]
        ]
    },
    {
        "id": "86a56fff.fd11d8",
        "type": "debug",
        "z": "9bff0843.525ed8",
        "name": "",
        "active": true,
        "tosidebar": true,
        "console": false,
        "tostatus": false,
        "complete": "true",
        "targetType": "full",
        "statusVal": "",
        "statusType": "auto",
        "x": 870,
        "y": 300,
        "wires": []
    },
    {
        "id": "aa03b7a9.435998",
        "type": "function",
        "z": "9bff0843.525ed8",
        "name": "",
        "func": "msg.topic = \"INSERT INTO `measurements` (`temp_in`) VALUES (:temp_in);\"\nreturn msg;",
        "outputs": 1,
        "noerr": 0,
        "initialize": "",
        "finalize": "",
        "x": 460,
        "y": 360,
        "wires": [
            [
                "b23e4b36.f9142"
            ]
        ]
    },
    {
        "id": "b23e4b36.f9142",
        "type": "Stackhero-MySQL",
        "z": "9bff0843.525ed8",
        "server": "89e0d4c3.dd5218",
        "name": "",
        "x": 690,
        "y": 440,
        "wires": [
            [
                "86a56fff.fd11d8"
            ]
        ]
    },
    {
        "id": "89e0d4c3.dd5218",
        "type": "Stackhero-MySQL-Server",
        "name": "",
        "host": "172.17.0.1",
        "port": "3306",
        "tls": false,
        "database": "collector"
    }
]
